yapps/__init__.py
yapps/cli_tool.py
yapps/grammar.py
yapps/parsetree.py
yapps/runtime.py
Yapps2_logilab-2.2.1.dist-info/LICENSE
Yapps2_logilab-2.2.1.dist-info/METADATA
Yapps2_logilab-2.2.1.dist-info/WHEEL
Yapps2_logilab-2.2.1.dist-info/entry_points.txt
Yapps2_logilab-2.2.1.dist-info/top_level.txt
Yapps2_logilab-2.2.1.dist-info/RECORD
